mcPackets/Packets.py
mcPackets/__init__.py
mcPackets/algorithm.py
mcPackets-1.1.dist-info/DESCRIPTION.rst
mcPackets-1.1.dist-info/METADATA
mcPackets-1.1.dist-info/RECORD
mcPackets-1.1.dist-info/WHEEL
mcPackets-1.1.dist-info/metadata.json
mcPackets-1.1.dist-info/top_level.txt
