Metadata-Version: 2.0
Name: mcPackets
Version: 1.1
Summary: 关于我的世界数据包生存的库!
Home-page: UNKNOWN
Author: 朝歌夜弦
Author-email: top@cvbop.cn
License: UNKNOWN
Platform: UNKNOWN
Requires-Dist: nbtlib
